<?xml version='1.0' encoding='UTF-8'?>
<flow-definition plugin="workflow-job@2.12.2">
  <actions>
    <org.jenkinsci.plugins.workflow.multibranch.JobPropertyTrackerAction plugin="workflow-multibranch@2.16">
      <jobPropertyDescriptors>
        <string>com.coravy.hudson.plugins.github.GithubProjectProperty</string>
        <string>jenkins.model.BuildDiscarderProperty</string>
      </jobPropertyDescriptors>
    </org.jenkinsci.plugins.workflow.multibranch.JobPropertyTrackerAction>
  </actions>
  <description>Addressbook Pipeline</description>
  <keepDependencies>false</keepDependencies>
  <properties>
    <hudson.model.ParametersDefinitionProperty>
      <parameterDefinitions>
        <hudson.model.BooleanParameterDefinition>
          <name>ISARCHIVALENABLED</name>
          <description></description>
          <defaultValue>false</defaultValue>
        </hudson.model.BooleanParameterDefinition>
        <hudson.model.BooleanParameterDefinition>
          <name>ISANALYSISENABLED</name>
          <description></description>
          <defaultValue>false</defaultValue>
        </hudson.model.BooleanParameterDefinition>
      </parameterDefinitions>
    </hudson.model.ParametersDefinitionProperty>
    <org.jenkinsci.plugins.workflow.job.properties.PipelineTriggersJobProperty>
      <triggers/>
    </org.jenkinsci.plugins.workflow.job.properties.PipelineTriggersJobProperty>
    <jenkins.model.BuildDiscarderProperty>
      <strategy class="hudson.tasks.LogRotator">
        <daysToKeep>5</daysToKeep>
        <numToKeep>5</numToKeep>
        <artifactDaysToKeep>5</artifactDaysToKeep>
        <artifactNumToKeep>5</artifactNumToKeep>
      </strategy>
    </jenkins.model.BuildDiscarderProperty>
    <com.coravy.hudson.plugins.github.GithubProjectProperty plugin="github@1.28.0">
      <projectUrl>https://github.com/veersudhir83/addressbook-vaadin.git/</projectUrl>
    </com.coravy.hudson.plugins.github.GithubProjectProperty>
  </properties>
  <definition class="org.jenkinsci.plugins.workflow.cps.CpsScmFlowDefinition" plugin="workflow-cps@2.40">
    <scm class="hudson.plugins.git.GitSCM" plugin="git@3.5.1">
      <configVersion>2</configVersion>
      <userRemoteConfigs>
        <hudson.plugins.git.UserRemoteConfig>
          <url>https://github.com/veersudhir83/DevOps-Pipeline.git</url>
          <credentialsId>e9de15d2-0c27-49da-9377-4b67c30fd275</credentialsId>
        </hudson.plugins.git.UserRemoteConfig>
      </userRemoteConfigs>
      <branches>
        <hudson.plugins.git.BranchSpec>
          <name>*/master</name>
        </hudson.plugins.git.BranchSpec>
      </branches>
      <doGenerateSubmoduleConfigurations>false</doGenerateSubmoduleConfigurations>
      <submoduleCfg class="list"/>
      <extensions/>
    </scm>
    <scriptPath>Addressbook-vaadin.groovy</scriptPath>
    <lightweight>true</lightweight>
  </definition>
  <triggers/>
  <disabled>false</disabled>
</flow-definition>